Metadata-Version: 2.1
Name: meu-investimento-fiap
Version: 0.2
Summary: Uma biblioteca para cálculos de investimentos.
Home-page: https://github.com/tadrianonet/meu_investimento
Author: Thiago S Adriano
Author-email: tadriano.dev@gmail.com
Classifier: Programming Language :: Python :: 3
Classifier: License :: OSI Approved :: MIT License
Classifier: Operating System :: OS Independent
Requires-Python: >=3.6
